src/design/keyboard_scanner.sv
module keyboard_scanner #(
    parameter CLK_HZ = 27_000_000
)(
    input  logic       clk,
    input  logic       reset,
    input  logic [3:0] rows,
    output logic [3:0] cols,
    output logic       key_valid,
    output logic [3:0] key_value
);

localparam SCAN_DIV = CLK_HZ / 4;
localparam DIV_BITS = $clog2(SCAN_DIV + 1);

logic [DIV_BITS-1:0] div_cnt;
logic                scan_tick;

// Divisor de frecuencia
always_ff @(posedge clk or posedge reset) begin
    if (reset) begin
        div_cnt   <= 0;
        scan_tick <= 0;
    end else if (div_cnt == SCAN_DIV - 1) begin
        div_cnt   <= 0;
        scan_tick <= 1;
    end else begin
        div_cnt   <= div_cnt + 1;
        scan_tick <= 0;
    end
end

// Contador de columna
logic [1:0] col_idx;

always_ff @(posedge clk or posedge reset) begin
    if (reset)
        col_idx <= 0;
    else if (scan_tick)
        col_idx <= col_idx + 1;
end

// Decodificacion de columna activa (activo bajo)
always_comb begin
    case (col_idx)
        2'd0: cols = 4'b1110;
        2'd1: cols = 4'b1101;
        2'd2: cols = 4'b1011;
        2'd3: cols = 4'b0111;
        default: cols = 4'b1111;
    endcase
end

// Deteccion de tecla
logic key_detected;

always_ff @(posedge clk or posedge reset) begin
    if (reset) begin
        key_valid    <= 0;
        key_value    <= 0;
        key_detected <= 0;
    end else begin
        key_valid <= 0;

        if (scan_tick) begin
            if (rows != 4'b1111 && !key_detected) begin
                key_detected <= 1;
                key_valid    <= 1;

                case ({rows, col_idx})
                    // Columna 0
                    {4'b1110, 2'd0}: key_value <= 4'd1;
                    {4'b1101, 2'd0}: key_value <= 4'd4;
                    {4'b1011, 2'd0}: key_value <= 4'd7;
                    {4'b0111, 2'd0}: key_value <= 4'hF; // *
                    // Columna 1
                    {4'b1110, 2'd1}: key_value <= 4'd2;
                    {4'b1101, 2'd1}: key_value <= 4'd5;
                    {4'b1011, 2'd1}: key_value <= 4'd8;
                    {4'b0111, 2'd1}: key_value <= 4'd0;
                    // Columna 2
                    {4'b1110, 2'd2}: key_value <= 4'd3;
                    {4'b1101, 2'd2}: key_value <= 4'd6;
                    {4'b1011, 2'd2}: key_value <= 4'd9;
                    {4'b0111, 2'd2}: key_value <= 4'hA; // #
                    // Columna 3
                    {4'b1110, 2'd3}: key_value <= 4'hA; // A
                    {4'b1101, 2'd3}: key_value <= 4'hB; // B
                    {4'b1011, 2'd3}: key_value <= 4'hC; // C
                    {4'b0111, 2'd3}: key_value <= 4'hD; // D
                    default:         key_value <= 4'hF;
                endcase

            end else if (rows == 4'b1111) begin
                key_detected <= 0;
            end
        end
    end
end

endmodule

src/sim/tb_keyboard.sv
`timescale 1ns/1ps

module tb_keyboard;

logic       clk, reset;
logic [3:0] rows;
logic [3:0] cols;
logic       key_valid;
logic [3:0] key_value;

// CLK_HZ=10 para que el scan_tick ocurra cada 10 ciclos
keyboard_scanner #(.CLK_HZ(10)) uut (
    .clk(clk),
    .reset(reset),
    .rows(rows),
    .cols(cols),
    .key_valid(key_valid),
    .key_value(key_value)
);

always #5 clk = ~clk;

initial begin
    $dumpfile("tb_keyboard.vcd");
    $dumpvars(0, tb_keyboard);

    clk = 0; reset = 1; rows = 4'b1111;
    #20 reset = 0;

    // Esperar varios ciclos de barrido
    #200;

    // Simular tecla "5": fila 1 activa (rows[1]=0)
    // col_idx estará en 1 en algún momento del barrido
    rows = 4'b1101;
    #200;
    rows = 4'b1111;
    #100;

    // Simular tecla "1": fila 0 activa
    rows = 4'b1110;
    #200;
    rows = 4'b1111;
    #100;

    // Simular tecla "#" (confirmacion): fila 3, columna 2
    rows = 4'b0111;
    #200;
    rows = 4'b1111;
    #100;

    $finish;
end

endmodule

src/build/tb_keyboard.vcd
$date
	Tue Apr 28 01:47:06 2026
$end
$version
	Icarus Verilog
$end
$timescale
	1ps
$end
$scope module tb_keyboard $end
$var wire 4 ! key_value [3:0] $end
$var wire 1 " key_valid $end
$var wire 4 # cols [3:0] $end
$var reg 1 $ clk $end
$var reg 1 % reset $end
$var reg 4 & rows [3:0] $end
$scope module uut $end
$var wire 1 $ clk $end
$var wire 1 % reset $end
$var wire 4 ' rows [3:0] $end
$var parameter 32 ( CLK_HZ $end
$var parameter 32 ) DIV_BITS $end
$var parameter 32 * SCAN_DIV $end
$var reg 2 + col_idx [1:0] $end
$var reg 4 , cols [3:0] $end
$var reg 2 - div_cnt [1:0] $end
$var reg 1 . key_detected $end
$var reg 1 " key_valid $end
$var reg 4 / key_value [3:0] $end
$var reg 1 0 scan_tick $end
$upscope $end
$upscope $end
$enddefinitions $end
$comment Show the parameter values. $end
$dumpall
b10 *
b10 )
b1010 (
$end
#0
$dumpvars
00
b0 /
0.
b0 -
b1110 ,
b0 +
b1111 '
b1111 &
1%
0$
b1110 #
0"
b0 !
$end
#5000
1$
#10000
0$
#15000
1$
#20000
0$
0%
#25000
b1 -
1$
#30000
0$
#35000
10
b0 -
1$
#40000
0$
#45000
b1101 #
b1101 ,
b1 +
00
b1 -
1$
#50000
0$
#55000
10
b0 -
1$
#60000
0$
#65000
b1011 #
b1011 ,
b10 +
00
b1 -
1$
#70000
0$
#75000
10
b0 -
1$
#80000
0$
#85000
b111 #
b111 ,
b11 +
00
b1 -
1$
#90000
0$
#95000
10
b0 -
1$
#100000
0$
#105000
b1110 #
b1110 ,
b0 +
00
b1 -
1$
#110000
0$
#115000
10
b0 -
1$
#120000
0$
#125000
b1101 #
b1101 ,
b1 +
00
b1 -
1$
#130000
0$
#135000
10
b0 -
1$
#140000
0$
#145000
b1011 #
b1011 ,
b10 +
00
b1 -
1$
#150000
0$
#155000
10
b0 -
1$
#160000
0$
#165000
b111 #
b111 ,
b11 +
00
b1 -
1$
#170000
0$
#175000
10
b0 -
1$
#180000
0$
#185000
b1110 #
b1110 ,
b0 +
00
b1 -
1$
#190000
0$
#195000
10
b0 -
1$
#200000
0$
#205000
b1101 #
b1101 ,
b1 +
00
b1 -
1$
#210000
0$
#215000
10
b0 -
1$
#220000
0$
b1101 &
b1101 '
#225000
b1011 #
b1011 ,
b101 !
b101 /
1"
1.
b10 +
00
b1 -
1$
#230000
0$
#235000
10
b0 -
0"
1$
#240000
0$
#245000
b111 #
b111 ,
b11 +
00
b1 -
1$
#250000
0$
#255000
10
b0 -
1$
#260000
0$
#265000
b1110 #
b1110 ,
b0 +
00
b1 -
1$
#270000
0$
#275000
10
b0 -
1$
#280000
0$
#285000
b1101 #
b1101 ,
b1 +
00
b1 -
1$
#290000
0$
#295000
10
b0 -
1$
#300000
0$
#305000
b1011 #
b1011 ,
b10 +
00
b1 -
1$
#310000
0$
#315000
10
b0 -
1$
#320000
0$
#325000
b111 #
b111 ,
b11 +
00
b1 -
1$
#330000
0$
#335000
10
b0 -
1$
#340000
0$
#345000
b1110 #
b1110 ,
b0 +
00
b1 -
1$
#350000
0$
#355000
10
b0 -
1$
#360000
0$
#365000
b1101 #
b1101 ,
b1 +
00
b1 -
1$
#370000
0$
#375000
10
b0 -
1$
#380000
0$
#385000
b1011 #
b1011 ,
b10 +
00
b1 -
1$
#390000
0$
#395000
10
b0 -
1$
#400000
0$
#405000
b111 #
b111 ,
b11 +
00
b1 -
1$
#410000
0$
#415000
10
b0 -
1$
#420000
0$
b1111 &
b1111 '
#425000
b1110 #
b1110 ,
0.
b0 +
00
b1 -
1$
#430000
0$
#435000
10
b0 -
1$
#440000
0$
#445000
b1101 #
b1101 ,
b1 +
00
b1 -
1$
#450000
0$
#455000
10
b0 -
1$
#460000
0$
#465000
b1011 #
b1011 ,
b10 +
00
b1 -
1$
#470000
0$
#475000
10
b0 -
1$
#480000
0$
#485000
b111 #
b111 ,
b11 +
00
b1 -
1$
#490000
0$
#495000
10
b0 -
1$
#500000
0$
#505000
b1110 #
b1110 ,
b0 +
00
b1 -
1$
#510000
0$
#515000
10
b0 -
1$
#520000
0$
b1110 &
b1110 '
#525000
b1101 #
b1101 ,
b1 !
b1 /
1"
1.
b1 +
00
b1 -
1$
#530000
0$
#535000
10
b0 -
0"
1$
#540000
0$
#545000
b1011 #
b1011 ,
b10 +
00
b1 -
1$
#550000
0$
#555000
10
b0 -
1$
#560000
0$
#565000
b111 #
b111 ,
b11 +
00
b1 -
1$
#570000
0$
#575000
10
b0 -
1$
#580000
0$
#585000
b1110 #
b1110 ,
b0 +
00
b1 -
1$
#590000
0$
#595000
10
b0 -
1$
#600000
0$
#605000
b1101 #
b1101 ,
b1 +
00
b1 -
1$
#610000
0$
#615000
10
b0 -
1$
#620000
0$
#625000
b1011 #
b1011 ,
b10 +
00
b1 -
1$
#630000
0$
#635000
10
b0 -
1$
#640000
0$
#645000
b111 #
b111 ,
b11 +
00
b1 -
1$
#650000
0$
#655000
10
b0 -
1$
#660000
0$
#665000
b1110 #
b1110 ,
b0 +
00
b1 -
1$
#670000
0$
#675000
10
b0 -
1$
#680000
0$
#685000
b1101 #
b1101 ,
b1 +
00
b1 -
1$
#690000
0$
#695000
10
b0 -
1$
#700000
0$
#705000
b1011 #
b1011 ,
b10 +
00
b1 -
1$
#710000
0$
#715000
10
b0 -
1$
#720000
0$
b1111 &
b1111 '
#725000
b111 #
b111 ,
0.
b11 +
00
b1 -
1$
#730000
0$
#735000
10
b0 -
1$
#740000
0$
#745000
b1110 #
b1110 ,
b0 +
00
b1 -
1$
#750000
0$
#755000
10
b0 -
1$
#760000
0$
#765000
b1101 #
b1101 ,
b1 +
00
b1 -
1$
#770000
0$
#775000
10
b0 -
1$
#780000
0$
#785000
b1011 #
b1011 ,
b10 +
00
b1 -
1$
#790000
0$
#795000
10
b0 -
1$
#800000
0$
#805000
b111 #
b111 ,
b11 +
00
b1 -
1$
#810000
0$
#815000
10
b0 -
1$
#820000
0$
b111 &
b111 '
#825000
b1110 #
b1110 ,
b1101 !
b1101 /
1"
1.
b0 +
00
b1 -
1$
#830000
0$
#835000
10
b0 -
0"
1$
#840000
0$
#845000
b1101 #
b1101 ,
b1 +
00
b1 -
1$
#850000
0$
#855000
10
b0 -
1$
#860000
0$
#865000
b1011 #
b1011 ,
b10 +
00
b1 -
1$
#870000
0$
#875000
10
b0 -
1$
#880000
0$
#885000
b111 #
b111 ,
b11 +
00
b1 -
1$
#890000
0$
#895000
10
b0 -
1$
#900000
0$
#905000
b1110 #
b1110 ,
b0 +
00
b1 -
1$
#910000
0$
#915000
10
b0 -
1$
#920000
0$
#925000
b1101 #
b1101 ,
b1 +
00
b1 -
1$
#930000
0$
#935000
10
b0 -
1$
#940000
0$
#945000
b1011 #
b1011 ,
b10 +
00
b1 -
1$
#950000
0$
#955000
10
b0 -
1$
#960000
0$
#965000
b111 #
b111 ,
b11 +
00
b1 -
1$
#970000
0$
#975000
10
b0 -
1$
#980000
0$
#985000
b1110 #
b1110 ,
b0 +
00
b1 -
1$
#990000
0$
#995000
10
b0 -
1$
#1000000
0$
#1005000
b1101 #
b1101 ,
b1 +
00
b1 -
1$
#1010000
0$
#1015000
10
b0 -
1$
#1020000
0$
b1111 &
b1111 '
#1025000
b1011 #
b1011 ,
0.
b10 +
00
b1 -
1$
#1030000
0$
#1035000
10
b0 -
1$
#1040000
0$
#1045000
b111 #
b111 ,
b11 +
00
b1 -
1$
#1050000
0$
#1055000
10
b0 -
1$
#1060000
0$
#1065000
b1110 #
b1110 ,
b0 +
00
b1 -
1$
#1070000
0$
#1075000
10
b0 -
1$
#1080000
0$
#1085000
b1101 #
b1101 ,
b1 +
00
b1 -
1$
#1090000
0$
#1095000
10
b0 -
1$
#1100000
0$
#1105000
b1011 #
b1011 ,
b10 +
00
b1 -
1$
#1110000
0$
#1115000
10
b0 -
1$
