src/design/seven_seg_decoder.sv
module seven_seg_decoder (
    input  [3:0] data_in,
    output reg [7:0] code_out
);

always @(*) begin
    case (data_in)
        4'd0: code_out = 8'b11111100;
        4'd1: code_out = 8'b01100000;
        4'd2: code_out = 8'b11011010;
        4'd3: code_out = 8'b11110010;
        4'd4: code_out = 8'b01100110;
        4'd5: code_out = 8'b10110110;
        4'd6: code_out = 8'b10111110;
        4'd7: code_out = 8'b11100000;
        4'd8: code_out = 8'b11111110;
        4'd9: code_out = 8'b11110110;
        default: code_out = 8'b00000000;
    endcase
end

endmodule

src/sim/tb_seven_seg.sv
`timescale 1ns/1ps

module tb_seven_seg;

    reg  [3:0] data_in;
    wire [7:0] code_out;

    seven_seg_decoder uut (
        .data_in(data_in),
        .code_out(code_out)
    );

    initial begin
        $dumpfile("test.vcd");
        $dumpvars(0, tb_seven_seg);

        data_in = 0; #10;
        data_in = 1; #10;
        data_in = 2; #10;
        data_in = 3; #10;
        data_in = 4; #10;
        data_in = 5; #10;
        data_in = 6; #10;
        data_in = 7; #10;
        data_in = 8; #10;
        data_in = 9; #10;

        $finish;
    end

endmodule

src/build/test.vcd
$date
	Tue Mar 31 23:00:35 2026
$end
$version
	Icarus Verilog
$end
$timescale
	1ps
$end
$scope module tb_seven_seg $end
$var wire 8 ! code_out [7:0] $end
$var reg 4 " data_in [3:0] $end
$scope module uut $end
$var wire 4 # data_in [3:0] $end
$var reg 8 $ code_out [7:0] $end
$upscope $end
$upscope $end
$enddefinitions $end
$comment Show the parameter values. $end
$dumpall
$end
#0
$dumpvars
b11111100 $
b0 #
b0 "
b11111100 !
$end
#10000
b1100000 !
b1100000 $
b1 "
b1 #
#20000
b11011010 !
b11011010 $
b10 "
b10 #
#30000
b11110010 !
b11110010 $
b11 "
b11 #
#40000
b1100110 !
b1100110 $
b100 "
b100 #
#50000
b10110110 !
b10110110 $
b101 "
b101 #
#60000
b10111110 !
b10111110 $
b110 "
b110 #
#70000
b11100000 !
b11100000 $
b111 "
b111 #
#80000
b11111110 !
b11111110 $
b1000 "
b1000 #
#90000
b11110110 !
b11110110 $
b1001 "
b1001 #
