src/design/keypad_reader.sv
module keypad_reader (
    input  logic clk,
    input  logic rst_n,
    output logic [3:0] filas,
    input  logic [3:0] columnas,
    output logic [3:0] key_value,
    output logic       key_valid
);

    parameter integer SCAN_DELAY    = 27000;
    parameter integer RELEASE_DELAY = 200000;

    logic [1:0]  fila_index;
    logic [15:0] scan_cnt;
    logic [17:0] release_cnt;

    logic [3:0] columnas_ff1;
    logic [3:0] columnas_sync;

    logic [3:0] col_read;
    logic [3:0] key_code;
    logic       detected;
    logic       locked;

    // Sincronizador de 2 flip-flops para entradas asíncronas del teclado
    always_ff @(posedge clk or negedge rst_n) begin
        if (!rst_n) begin
            columnas_ff1  <= 4'hF;
            columnas_sync <= 4'hF;
        end else begin
            columnas_ff1  <= columnas;
            columnas_sync <= columnas_ff1;
        end
    end

    always_ff @(posedge clk or negedge rst_n) begin
        if (!rst_n) begin
            scan_cnt <= 0;
            fila_index <= 0;
        end else if (!locked) begin
            if (scan_cnt == SCAN_DELAY - 1) begin
                scan_cnt <= 0;
                fila_index <= fila_index + 1;
            end else begin
                scan_cnt <= scan_cnt + 1;
            end
        end
    end

    always_comb begin
        case (fila_index)
            2'd0: filas = 4'b1110; // * 0 # D
            2'd1: filas = 4'b1101; // 7 8 9 C
            2'd2: filas = 4'b1011; // 4 5 6 B
            2'd3: filas = 4'b0111; // 1 2 3 A
            default: filas = 4'b1111;
        endcase
    end

    always_ff @(posedge clk or negedge rst_n) begin
        if (!rst_n)
            col_read <= 4'hF;
        else
            col_read <= columnas_sync;
    end

    always_comb begin
        key_code = 4'h0;
        detected = 1'b0;

        case (fila_index)
            2'd0: begin
                case (col_read)
                    4'hE: begin key_code = 4'hE; detected = 1'b1; end // *
                    4'hD: begin key_code = 4'h0; detected = 1'b1; end // 0
                    4'hB: begin key_code = 4'hF; detected = 1'b1; end // #
                    4'h7: begin key_code = 4'hD; detected = 1'b1; end // D
                    default: detected = 1'b0;
                endcase
            end

            2'd1: begin
                case (col_read)
                    4'hE: begin key_code = 4'h7; detected = 1'b1; end
                    4'hD: begin key_code = 4'h8; detected = 1'b1; end
                    4'hB: begin key_code = 4'h9; detected = 1'b1; end
                    4'h7: begin key_code = 4'hC; detected = 1'b1; end
                    default: detected = 1'b0;
                endcase
            end

            2'd2: begin
                case (col_read)
                    4'hE: begin key_code = 4'h4; detected = 1'b1; end
                    4'hD: begin key_code = 4'h5; detected = 1'b1; end
                    4'hB: begin key_code = 4'h6; detected = 1'b1; end
                    4'h7: begin key_code = 4'hB; detected = 1'b1; end
                    default: detected = 1'b0;
                endcase
            end

            2'd3: begin
                case (col_read)
                    4'hE: begin key_code = 4'h1; detected = 1'b1; end
                    4'hD: begin key_code = 4'h2; detected = 1'b1; end
                    4'hB: begin key_code = 4'h3; detected = 1'b1; end
                    4'h7: begin key_code = 4'hA; detected = 1'b1; end
                    default: detected = 1'b0;
                endcase
            end

            default: detected = 1'b0;
        endcase
    end

    always_ff @(posedge clk or negedge rst_n) begin
        if (!rst_n) begin
            key_value <= 4'd0;
            key_valid <= 1'b0;
            locked <= 1'b0;
            release_cnt <= 0;
        end else begin
            key_valid <= 1'b0;

            if (!locked && detected) begin
                key_value <= key_code;
                key_valid <= 1'b1;
                locked <= 1'b1;
                release_cnt <= 0;
            end else if (locked) begin
                if (col_read == 4'hF) begin
                    if (release_cnt < RELEASE_DELAY)
                        release_cnt <= release_cnt + 1;
                    else begin
                        locked <= 1'b0;
                        release_cnt <= 0;
                    end
                end else begin
                    release_cnt <= 0;
                end
            end
        end
    end

endmodule

Proyecto_3/Referencias/srcpry2/sim/tb_keypad_reader.sv
`timescale 1ns/1ps

module tb_keypad_reader;

    logic clk;
    logic rst_n;

    logic [3:0] filas;
    logic [3:0] columnas;

    logic [3:0] key_value;
    logic       key_valid;

    keypad_reader dut (
        .clk(clk),
        .rst_n(rst_n),
        .filas(filas),
        .columnas(columnas),
        .key_value(key_value),
        .key_valid(key_valid)
    );

    defparam dut.SCAN_DELAY = 10;
    defparam dut.RELEASE_DELAY = 20;

    initial begin
        clk = 0;
        forever #5 clk = ~clk;
    end

    initial begin
        $dumpfile("tb_keypad_reader.vcd");
        $dumpvars(0, tb_keypad_reader);

        columnas = 4'hF;
        rst_n = 0;

        repeat (5) @(posedge clk);
        rst_n = 1;
        repeat (20) @(posedge clk);

        test_key(4'h1);
        test_key(4'h2);
        test_key(4'h3);
        test_key(4'h4);
        test_key(4'h5);
        test_key(4'h6);
        test_key(4'h7);
        test_key(4'h8);
        test_key(4'h9);
        test_key(4'h0);
        test_key(4'hA);
        test_key(4'hB);
        test_key(4'hC);
        test_key(4'hD);
        test_key(4'hE); // *
        test_key(4'hF); // #

        $display("FIN tb_keypad_reader");
        $finish;
    end

    task test_key(input logic [3:0] key);
        logic [3:0] target_row;
        logic [3:0] target_col;
        logic detected_ok;
        begin
            key_to_row_col(key, target_row, target_col);
            detected_ok = 1'b0;

            wait (filas == target_row);

            columnas = target_col;

            repeat (80) begin
                @(posedge clk);
                if (key_valid && key_value == key)
                    detected_ok = 1'b1;
            end

            columnas = 4'hF;
            repeat (80) @(posedge clk);

            if (detected_ok)
                $display("OK tecla %h detectada correctamente", key);
            else
                $display("ERROR tecla %h no detectada correctamente. key_value=%h key_valid=%b",
                         key, key_value, key_valid);
        end
    endtask

    task key_to_row_col(
        input  logic [3:0] key,
        output logic [3:0] row,
        output logic [3:0] col
    );
        begin
            row = 4'hF;
            col = 4'hF;

            case (key)
                4'h1: begin row = 4'b0111; col = 4'hE; end
                4'h2: begin row = 4'b0111; col = 4'hD; end
                4'h3: begin row = 4'b0111; col = 4'hB; end
                4'hA: begin row = 4'b0111; col = 4'h7; end

                4'h4: begin row = 4'b1011; col = 4'hE; end
                4'h5: begin row = 4'b1011; col = 4'hD; end
                4'h6: begin row = 4'b1011; col = 4'hB; end
                4'hB: begin row = 4'b1011; col = 4'h7; end

                4'h7: begin row = 4'b1101; col = 4'hE; end
                4'h8: begin row = 4'b1101; col = 4'hD; end
                4'h9: begin row = 4'b1101; col = 4'hB; end
                4'hC: begin row = 4'b1101; col = 4'h7; end

                4'hE: begin row = 4'b1110; col = 4'hE; end // *
                4'h0: begin row = 4'b1110; col = 4'hD; end
                4'hF: begin row = 4'b1110; col = 4'hB; end // #
                4'hD: begin row = 4'b1110; col = 4'h7; end
            endcase
        end
    endtask

endmodule

Proyecto_3/Referencias/srcpry2/build/tb_keypad_reader.vcd
$date
	Mon May 04 23:57:03 2026
$end
$version
	Icarus Verilog
$end
$timescale
	1ps
$end
$scope module tb_keypad_reader $end
$var wire 4 ! key_value [3:0] $end
$var wire 1 " key_valid $end
$var wire 4 # filas [3:0] $end
$var reg 1 $ clk $end
$var reg 4 % columnas [3:0] $end
$var reg 1 & rst_n $end
$scope module dut $end
$var wire 1 $ clk $end
$var wire 4 ' columnas [3:0] $end
$var wire 1 & rst_n $end
$var parameter 32 ( RELEASE_DELAY $end
$var parameter 32 ) SCAN_DELAY $end
$var reg 4 * col_read [3:0] $end
$var reg 4 + columnas_ff1 [3:0] $end
$var reg 4 , columnas_sync [3:0] $end
$var reg 1 - detected $end
$var reg 2 . fila_index [1:0] $end
$var reg 4 / filas [3:0] $end
$var reg 4 0 key_code [3:0] $end
$var reg 1 " key_valid $end
$var reg 4 1 key_value [3:0] $end
$var reg 1 2 locked $end
$var reg 18 3 release_cnt [17:0] $end
$var reg 16 4 scan_cnt [15:0] $end
$upscope $end
$scope task key_to_row_col $end
$var reg 4 5 col [3:0] $end
$var reg 4 6 key [3:0] $end
$var reg 4 7 row [3:0] $end
$upscope $end
$scope task test_key $end
$var reg 1 8 detected_ok $end
$var reg 4 9 key [3:0] $end
$var reg 4 : target_col [3:0] $end
$var reg 4 ; target_row [3:0] $end
$upscope $end
$upscope $end
$enddefinitions $end
$comment Show the parameter values. $end
$dumpall
b1010 )
b10100 (
$end
#0
$dumpvars
bx ;
bx :
bx 9
x8
bx 7
bx 6
bx 5
b0 4
b0 3
02
b0 1
b0 0
b1110 /
b0 .
0-
b1111 ,
b1111 +
b1111 *
b1111 '
0&
b1111 %
0$
b1110 #
0"
b0 !
$end
#5000
1$
#10000
0$
#15000
1$
#20000
0$
#25000
1$
#30000
0$
#35000
1$
#40000
0$
#45000
b1 4
1&
1$
#50000
0$
#55000
b10 4
1$
#60000
0$
#65000
b11 4
1$
#70000
0$
#75000
b100 4
1$
#80000
0$
#85000
b101 4
1$
#90000
0$
#95000
b110 4
1$
#100000
0$
#105000
b111 4
1$
#110000
0$
#115000
b1000 4
1$
#120000
0$
#125000
b1001 4
1$
#130000
0$
#135000
b1101 #
b1101 /
b1 .
b0 4
1$
#140000
0$
#145000
b1 4
1$
#150000
0$
#155000
b10 4
1$
#160000
0$
#165000
b11 4
1$
#170000
0$
#175000
b100 4
1$
#180000
0$
#185000
b101 4
1$
#190000
0$
#195000
b110 4
1$
#200000
0$
#205000
b111 4
1$
#210000
0$
#215000
b1000 4
1$
#220000
0$
#225000
b1001 4
1$
#230000
0$
#235000
b1011 #
b1011 /
b10 .
b0 4
1$
#240000
0$
#245000
b1 4
08
b1110 :
b111 ;
b1110 5
b111 7
b1 6
b1 9
1$
#250000
0$
#255000
b10 4
1$
#260000
0$
#265000
b11 4
1$
#270000
0$
#275000
b100 4
1$
#280000
0$
#285000
b101 4
1$
#290000
0$
#295000
b110 4
1$
#300000
0$
#305000
b111 4
1$
#310000
0$
#315000
b1000 4
1$
#320000
0$
#325000
b1001 4
1$
#330000
0$
#335000
b1110 %
b1110 '
b111 #
b111 /
b11 .
b0 4
1$
#340000
0$
#345000
b1 4
b1110 +
1$
#350000
0$
#355000
b1110 ,
b10 4
1$
#360000
0$
#365000
1-
b1 0
b1110 *
b11 4
1$
#370000
0$
#375000
b100 4
12
1"
b1 !
b1 1
1$
#380000
0$
#385000
0"
18
1$
